pykeyboard/__init__.py
pykeyboard/keys.py
pykeyinput/__init__.py
pykeyinput/keys.py
pykeyboard_input-0.0.2.1.dist-info/METADATA
pykeyboard_input-0.0.2.1.dist-info/WHEEL
pykeyboard_input-0.0.2.1.dist-info/top_level.txt
pykeyboard_input-0.0.2.1.dist-info/RECORD
