Metadata-Version: 2.1
Name: pykeyboard-input
Version: 0.0.2.1
Summary: Just a package i used in many projects to get which key pressed from keyboard
Home-page: UNKNOWN
Author: Emam_ahsour
Author-email: emam54637@gmail.com
License: UNKNOWN
Keywords: python,keyboard,tools,pycv2,inputs
Platform: UNKNOWN
Classifier: Development Status :: 1 - Planning
Classifier: Intended Audience :: Developers
Classifier: Programming Language :: Python :: 3
Classifier: Operating System :: Unix
Classifier: Operating System :: MacOS :: MacOS X
Classifier: Operating System :: Microsoft :: Windows
Requires-Dist: pywin32
